.bumpversion.cfg
.virtualenv.dev-requirements.txt
.virtualenv.requirements.txt
LICENSE
MANIFEST.in
Makefile
README.rst
setup.cfg
setup.py
tox.ini
cloud_builder/__init__.py
cloud_builder/cb_collect.py
cloud_builder/cb_ctl.py
cloud_builder/cb_fetch.py
cloud_builder/cb_image.py
cloud_builder/cb_info.py
cloud_builder/cb_prepare.py
cloud_builder/cb_run.py
cloud_builder/cb_scheduler.py
cloud_builder/cloud_logger.py
cloud_builder/defaults.py
cloud_builder/exceptions.py
cloud_builder/identity.py
cloud_builder/version.py
cloud_builder.egg-info/PKG-INFO
cloud_builder.egg-info/SOURCES.txt
cloud_builder.egg-info/dependency_links.txt
cloud_builder.egg-info/entry_points.txt
cloud_builder.egg-info/not-zip-safe
cloud_builder.egg-info/requires.txt
cloud_builder.egg-info/top_level.txt
cloud_builder/broker/__init__.py
cloud_builder/broker/base.py
cloud_builder/broker/kafka.py
cloud_builder/broker/kafka_proxy.py
cloud_builder/broker/ssh_kafka/__init__.py
cloud_builder/broker/ssh_kafka/ssh_kafka_read.py
cloud_builder/broker/ssh_kafka/ssh_kafka_write.py
cloud_builder/build_request/__init__.py
cloud_builder/build_request/build_request.py
cloud_builder/build_request/build_request_schema.py
cloud_builder/config/cbctl_schema.py
cloud_builder/config/cloud_builder_broker_schema.py
cloud_builder/info_request/__init__.py
cloud_builder/info_request/info_request.py
cloud_builder/info_request/info_request_schema.py
cloud_builder/info_response/__init__.py
cloud_builder/info_response/info_response.py
cloud_builder/info_response/info_response_schema.py
cloud_builder/project_metadata/__init__.py
cloud_builder/project_metadata/project_metadata.py
cloud_builder/project_metadata/project_metadata_schema.py
cloud_builder/response/__init__.py
cloud_builder/response/response.py
cloud_builder/response/response_schema.py
cloud_builder/utils/__init__.py
cloud_builder/utils/display.py
cloud_builder/utils/git.py
cloud_builder/utils/repository.py
completion/cb-ctl
etc/cloud_builder
package/python-cloud_builder-rpmlintrc
package/python-cloud_builder-spec-template
package/python-cloud_builder.changes
systemd/cb-collect.service
systemd/cb-fetch-once.service
systemd/cb-fetch.service
systemd/cb-info.service
systemd/cb-scheduler.service