Metadata-Version: 2.1
Name: cloud-builder
Version: 1.0.6
Summary: Cloud Builder
Home-page: UNKNOWN
Author: Marcus Schaefer
Author-email: marcus.schaefer@gmail.com
License: GPLv3+
Platform: UNKNOWN
Classifier: Development Status :: 1 - Planning
Classifier: Intended Audience :: Developers
Classifier: License :: OSI Approved :: GNU General Public License v3 or later (GPLv3+)
Classifier: Operating System :: POSIX :: Linux
Classifier: Programming Language :: Python :: 3.6
Classifier: Programming Language :: Python :: 3.7
Classifier: Topic :: System :: Operating System
Requires-Python: >=3.6
License-File: LICENSE
